kier/__init__.py
kier-0.1.0.dist-info/METADATA
kier-0.1.0.dist-info/WHEEL
kier-0.1.0.dist-info/licenses/LICENSE
kier-0.1.0.dist-info/RECORD
